owowen/__init__.py
owowen/api.py
owowen/classes/__init__.py
owowen/classes/movie.py
owowen-0.1.0.dist-info/LICENSE
owowen-0.1.0.dist-info/METADATA
owowen-0.1.0.dist-info/WHEEL
owowen-0.1.0.dist-info/top_level.txt
owowen-0.1.0.dist-info/RECORD
