Metadata-Version: 2.1
Name: owowen
Version: 0.1.0
Summary: A Python client library for the Owen Wilson Wow API
Home-page: https://github.com/nwithan8/owowen
Author: Nate Harris
Author-email: n8gr8gbln@gmail.com
License: GNU General Public License v3 (GPLv3)
Download-URL: https://github.com/nwithan8/owowen/archive/refs/tags/0.1.0.tar.gz
Keywords: Owen Wilson,wow,API,movies,directors,nwithan8
Platform: UNKNOWN
Classifier: License :: OSI Approved :: GNU General Public License v3 (GPLv3)
Classifier: Development Status :: 4 - Beta
Classifier: Intended Audience :: Developers
Classifier: Topic :: Software Development :: Build Tools
Classifier: Programming Language :: Python :: 3
Classifier: Programming Language :: Python :: 3.8
Classifier: Programming Language :: Python :: 3.9
Classifier: Programming Language :: Python :: 3.10
Classifier: Topic :: Multimedia
Classifier: Topic :: Internet :: WWW/HTTP
Classifier: Operating System :: OS Independent
Requires-Python: >=3.8, <4
License-File: LICENSE
Requires-Dist: setuptools (~=60.2.0)
Requires-Dist: objectrest (~=1.2.0)
